{"id": 1206355174387802113, "conversation_id": "1206355174387802113", "created_at": "2019-12-15 23:27:41 GMT", "date": "2019-12-15", "time": "23:27:41", "timezone": "+0000", "user_id": 2720985663, "username": "runnermarathon1", "name": "James Allen", "place": "", "tweet": "Exactly when is it ever going to stop raining.....?!! It’s been so long now I can’t remember the last time it stayed dry for a whole day #starting work on my houseboat #floods #rain #rain #rain 🌧🌧🌧💦☔️💨", "language": "en", "mentions": [], "urls": [], "photos": [], "replies_count": 0, "retweets_count": 0, "likes_count": 0, "hashtags": ["starting", "floods", "rain", "rain", "rain"], "cashtags": [], "link": "https://twitter.com/runnermarathon1/status/1206355174387802113", "retweet": false, "quote_url": "", "video": 0, "thumbnail": "", "near": "", "geo": "54.153709,-4.529766,527km", "source": "", "user_rt_id": "", "user_rt": "", "retweet_id": "", "reply_to": [], "retweet_date": "", "translate": "", "trans_src": "", "trans_dest": ""}
{"id": 1206334870198329344, "conversation_id": "1206334870198329344", "created_at": "2019-12-15 22:07:00 GMT", "date": "2019-12-15", "time": "22:07:00", "timezone": "+0000", "user_id": 2320501254, "username": "timmystubbs", "name": "Tim Stubbs", "place": "", "tweet": "If you look carefully enough, you can plainly see the flood plane. #walking soundtrack @hot_natured Different Sides of the Sun. #photooftheday #photography #amateurphotography #sunday  https://t.co/lt9OOOLh6Y", "language": "en", "mentions": [{"screen_name": "hot_natured", "name": "hot natured", "id": "974080057"}], "urls": [], "photos": ["https://pbs.twimg.com/media/EL3DJkMXUAAJJFU.jpg"], "replies_count": 0, "retweets_count": 0, "likes_count": 0, "hashtags": ["walking", "photooftheday", "photography", "amateurphotography", "sunday"], "cashtags": [], "link": "https://twitter.com/TimmyStubbs/status/1206334870198329344", "retweet": false, "quote_url": "", "video": 1, "thumbnail": "https://pbs.twimg.com/media/EL3DJkMXUAAJJFU.jpg", "near": "", "geo": "54.153709,-4.529766,527km", "source": "", "user_rt_id": "", "user_rt": "", "retweet_id": "", "reply_to": [], "retweet_date": "", "translate": "", "trans_src": "", "trans_dest": ""}
{"id": 1206332445802545152, "conversation_id": "1206332445802545152", "created_at": "2019-12-15 21:57:22 GMT", "date": "2019-12-15", "time": "21:57:22", "timezone": "+0000", "user_id": 815716761614118912, "username": "willisrm73", "name": "Dr Rich Willis", "place": "", "tweet": "French 5e Armée, On vacating their 1st position trenches proceeded to flood them with Yperite gas. So when Germans occupied same trenches on morning of 15th July 1918 they were immediately forced out of the shelters &amp; exposed to waiting French guns. #2ndMarne #GasWarfare", "language": "en", "mentions": [], "urls": [], "photos": [], "replies_count": 0, "retweets_count": 0, "likes_count": 7, "hashtags": ["2ndmarne", "gaswarfare"], "cashtags": [], "link": "https://twitter.com/willisRM73/status/1206332445802545152", "retweet": false, "quote_url": "", "video": 0, "thumbnail": "", "near": "", "geo": "54.153709,-4.529766,527km", "source": "", "user_rt_id": "", "user_rt": "", "retweet_id": "", "reply_to": [], "retweet_date": "", "translate": "", "trans_src": "", "trans_dest": ""}
{"id": 1206328213645021184, "conversation_id": "1206328213645021184", "created_at": "2019-12-15 21:40:33 GMT", "date": "2019-12-15", "time": "21:40:33", "timezone": "+0000", "user_id": 3446146816, "username": "riverlevelsuk", "name": "River Levels UK", "place": {"type": "Point", "coordinates": [51.530834, -2.053319]}, "tweet": "Flood Alert: Upper Bristol Avon Area 21:30 15 December  https://t.co/yn4V8ZzRyh", "language": "en", "mentions": [], "urls": ["https://riverlevels.uk/flood-warning-upper-bristol-avon-area/1576446032"], "photos": [], "replies_count": 0, "retweets_count": 0, "likes_count": 0, "hashtags": [], "cashtags": [], "link": "https://twitter.com/RiverlevelsUK/status/1206328213645021184", "retweet": false, "quote_url": "", "video": 0, "thumbnail": "", "near": "", "geo": "54.153709,-4.529766,527km", "source": "", "user_rt_id": "", "user_rt": "", "retweet_id": "", "reply_to": [], "retweet_date": "", "translate": "", "trans_src": "", "trans_dest": ""}
{"id": 1206328190823780355, "conversation_id": "1206328190823780355", "created_at": "2019-12-15 21:40:27 GMT", "date": "2019-12-15", "time": "21:40:27", "timezone": "+0000", "user_id": 3446146816, "username": "riverlevelsuk", "name": "River Levels UK", "place": {"type": "Point", "coordinates": [51.344343, -2.137721]}, "tweet": "Flood Alert: Mid Bristol Avon Area 21:25 15 December  https://t.co/yyIqRtrEC7", "language": "en", "mentions": [], "urls": ["https://riverlevels.uk/flood-warning-mid-bristol-avon-area/1576446027"], "photos": [], "replies_count": 0, "retweets_count": 0, "likes_count": 0, "hashtags": [], "cashtags": [], "link": "https://twitter.com/RiverlevelsUK/status/1206328190823780355", "retweet": false, "quote_url": "", "video": 0, "thumbnail": "", "near": "", "geo": "54.153709,-4.529766,527km", "source": "", "user_rt_id": "", "user_rt": "", "retweet_id": "", "reply_to": [], "retweet_date": "", "translate": "", "trans_src": "", "trans_dest": ""}
{"id": 1206328168010993664, "conversation_id": "1206328168010993664", "created_at": "2019-12-15 21:40:22 GMT", "date": "2019-12-15", "time": "21:40:22", "timezone": "+0000", "user_id": 3446146816, "username": "riverlevelsuk", "name": "River Levels UK", "place": {"type": "Point", "coordinates": [50.728812, -2.222055]}, "tweet": "Flood Alert: River Piddle and tributaries 21:19 15 December  https://t.co/1EUbWGGyKW", "language": "en", "mentions": [], "urls": ["https://riverlevels.uk/flood-warning-river-piddle-and-tributaries/1576446022"], "photos": [], "replies_count": 0, "retweets_count": 0, "likes_count": 0, "hashtags": [], "cashtags": [], "link": "https://twitter.com/RiverlevelsUK/status/1206328168010993664", "retweet": false, "quote_url": "", "video": 0, "thumbnail": "", "near": "", "geo": "54.153709,-4.529766,527km", "source": "", "user_rt_id": "", "user_rt": "", "retweet_id": "", "reply_to": [], "retweet_date": "", "translate": "", "trans_src": "", "trans_dest": ""}
{"id": 1206325719204335616, "conversation_id": "1206325719204335616", "created_at": "2019-12-15 21:30:38 GMT", "date": "2019-12-15", "time": "21:30:38", "timezone": "+0000", "user_id": 3446146816, "username": "riverlevelsuk", "name": "River Levels UK", "place": {"type": "Point", "coordinates": [50.827208, -2.967777]}, "tweet": "Flood Alert: River Axe Area 21:03 15 December  https://t.co/qAkr1YtfFN", "language": "en", "mentions": [], "urls": ["https://riverlevels.uk/flood-warning-river-axe-area/1576445438"], "photos": [], "replies_count": 0, "retweets_count": 0, "likes_count": 0, "hashtags": [], "cashtags": [], "link": "https://twitter.com/RiverlevelsUK/status/1206325719204335616", "retweet": false, "quote_url": "", "video": 0, "thumbnail": "", "near": "", "geo": "54.153709,-4.529766,527km", "source": "", "user_rt_id": "", "user_rt": "", "retweet_id": "", "reply_to": [], "retweet_date": "", "translate": "", "trans_src": "", "trans_dest": ""}
{"id": 1206325696458563588, "conversation_id": "1206325696458563588", "created_at": "2019-12-15 21:30:33 GMT", "date": "2019-12-15", "time": "21:30:33", "timezone": "+0000", "user_id": 3446146816, "username": "riverlevelsuk", "name": "River Levels UK", "place": {"type": "Point", "coordinates": [51.287474, -2.207444]}, "tweet": "Flood Alert: River Biss catchment 21:14 15 December  https://t.co/5JIF8oGKsP", "language": "en", "mentions": [], "urls": ["https://riverlevels.uk/flood-warning-river-biss-catchment/1576445432"], "photos": [], "replies_count": 0, "retweets_count": 0, "likes_count": 0, "hashtags": [], "cashtags": [], "link": "https://twitter.com/RiverlevelsUK/status/1206325696458563588", "retweet": false, "quote_url": "", "video": 0, "thumbnail": "", "near": "", "geo": "54.153709,-4.529766,527km", "source": "", "user_rt_id": "", "user_rt": "", "retweet_id": "", "reply_to": [], "retweet_date": "", "translate": "", "trans_src": "", "trans_dest": ""}
{"id": 1206325673842921474, "conversation_id": "1206325673842921474", "created_at": "2019-12-15 21:30:27 GMT", "date": "2019-12-15", "time": "21:30:27", "timezone": "+0000", "user_id": 3446146816, "username": "riverlevelsuk", "name": "River Levels UK", "place": {"type": "Point", "coordinates": [51.240095, -2.3479]}, "tweet": "Flood Alert: Somerset Frome Area 21:07 15 December  https://t.co/hxPI0uY92P", "language": "en", "mentions": [], "urls": ["https://riverlevels.uk/flood-warning-somerset-frome-area/1576445427"], "photos": [], "replies_count": 0, "retweets_count": 0, "likes_count": 0, "hashtags": [], "cashtags": [], "link": "https://twitter.com/RiverlevelsUK/status/1206325673842921474", "retweet": false, "quote_url": "", "video": 0, "thumbnail": "", "near": "", "geo": "54.153709,-4.529766,527km", "source": "", "user_rt_id": "", "user_rt": "", "retweet_id": "", "reply_to": [], "retweet_date": "", "translate": "", "trans_src": "", "trans_dest": ""}
{"id": 1206325650992312328, "conversation_id": "1206325650992312328", "created_at": "2019-12-15 21:30:22 GMT", "date": "2019-12-15", "time": "21:30:22", "timezone": "+0000", "user_id": 3446146816, "username": "riverlevelsuk", "name": "River Levels UK", "place": {"type": "Point", "coordinates": [51.866227, -1.172761]}, "tweet": "Flood Alert: Langford and Wendlebury Brooks from Stratton Audley down to near Merton 21:01 15 December  https://t.co/YUJ4Q40LWR", "language": "en", "mentions": [], "urls": ["https://riverlevels.uk/flood-warning-langford-and-wendlebury-brooks-from-stratton-audley-down-to-near-merton/1576445421"], "photos": [], "replies_count": 0, "retweets_count": 0, "likes_count": 0, "hashtags": [], "cashtags": [], "link": "https://twitter.com/RiverlevelsUK/status/1206325650992312328", "retweet": false, "quote_url": "", "video": 0, "thumbnail": "", "near": "", "geo": "54.153709,-4.529766,527km", "source": "", "user_rt_id": "", "user_rt": "", "retweet_id": "", "reply_to": [], "retweet_date": "", "translate": "", "trans_src": "", "trans_dest": ""}
{"id": 1206322175734452224, "conversation_id": "1206322175734452224", "created_at": "2019-12-15 21:16:33 GMT", "date": "2019-12-15", "time": "21:16:33", "timezone": "+0000", "user_id": 705994686, "username": "dailyderbys", "name": "DERBYSHIRE", "place": {"type": "Point", "coordinates": [52.91765398, -1.46989346]}, "tweet": "Heavy rainfall sparks Derbyshire flood alert  https://t.co/6OCQn2gtqG  https://t.co/uqlxbmDYe3", "language": "en", "mentions": [], "urls": ["http://j.mp/2RSe80K"], "photos": ["https://pbs.twimg.com/media/EL23oDWVAAAyr93.jpg"], "replies_count": 0, "retweets_count": 0, "likes_count": 0, "hashtags": [], "cashtags": [], "link": "https://twitter.com/DailyDERBYS/status/1206322175734452224", "retweet": false, "quote_url": "", "video": 1, "thumbnail": "https://pbs.twimg.com/media/EL23oDWVAAAyr93.jpg", "near": "", "geo": "54.153709,-4.529766,527km", "source": "", "user_rt_id": "", "user_rt": "", "retweet_id": "", "reply_to": [], "retweet_date": "", "translate": "", "trans_src": "", "trans_dest": ""}
{"id": 1206322122680930305, "conversation_id": "1206318505202765824", "created_at": "2019-12-15 21:16:21 GMT", "date": "2019-12-15", "time": "21:16:21", "timezone": "+0000", "user_id": 50060624, "username": "tom220love", "name": "tom jeffries🤘", "place": "", "tweet": "@DanielPCarter @BBCR1 @MCRofficial Let's see how emotional I get listening to this let's get it dan! My happy Teenage years are coming flooding back", "language": "en", "mentions": [], "urls": [], "photos": [], "replies_count": 0, "retweets_count": 0, "likes_count": 0, "hashtags": [], "cashtags": [], "link": "https://twitter.com/tom220love/status/1206322122680930305", "retweet": false, "quote_url": "", "video": 0, "thumbnail": "", "near": "", "geo": "54.153709,-4.529766,527km", "source": "", "user_rt_id": "", "user_rt": "", "retweet_id": "", "reply_to": [{"screen_name": "DanielPCarter", "name": "𝕯𝖆𝖓𝖎𝖊𝖑 𝕻 𝕮𝖆𝖗𝖙𝖊𝖗", "id": "250557161"}, {"screen_name": "BBCR1", "name": "BBC Radio 1", "id": "7111412"}, {"screen_name": "MCRofficial", "name": "My Chemical Romance", "id": "89018574"}], "retweet_date": "", "translate": "", "trans_src": "", "trans_dest": ""}
{"id": 1206320668712853505, "conversation_id": "1206320668712853505", "created_at": "2019-12-15 21:10:34 GMT", "date": "2019-12-15", "time": "21:10:34", "timezone": "+0000", "user_id": 3446146816, "username": "riverlevelsuk", "name": "River Levels UK", "place": {"type": "Point", "coordinates": [52.29031, -0.121828]}, "tweet": "Flood Alert: Lower River Great Ouse in Central Bedfordshire, Bedford Borough and Cambridgeshire 20:46 15 December  https://t.co/zowKDLdHBp", "language": "en", "mentions": [], "urls": ["https://riverlevels.uk/flood-warning-lower-river-great-ouse-in-central-bedfordshire-bedford-borough-and-cambridgeshire/1576444234"], "photos": [], "replies_count": 0, "retweets_count": 0, "likes_count": 0, "hashtags": [], "cashtags": [], "link": "https://twitter.com/RiverlevelsUK/status/1206320668712853505", "retweet": false, "quote_url": "", "video": 0, "thumbnail": "", "near": "", "geo": "54.153709,-4.529766,527km", "source": "", "user_rt_id": "", "user_rt": "", "retweet_id": "", "reply_to": [], "retweet_date": "", "translate": "", "trans_src": "", "trans_dest": ""}
{"id": 1206320645992267777, "conversation_id": "1206320645992267777", "created_at": "2019-12-15 21:10:29 GMT", "date": "2019-12-15", "time": "21:10:29", "timezone": "+0000", "user_id": 3446146816, "username": "riverlevelsuk", "name": "River Levels UK", "place": {"type": "Point", "coordinates": [50.966845, -2.856114]}, "tweet": "Flood Alert: South Somerset Rivers, Upper Reaches 20:50 15 December  https://t.co/mK7iI1qARC", "language": "en", "mentions": [], "urls": ["https://riverlevels.uk/flood-warning-south-somerset-rivers-upper-reaches/1576444228"], "photos": [], "replies_count": 0, "retweets_count": 0, "likes_count": 0, "hashtags": [], "cashtags": [], "link": "https://twitter.com/RiverlevelsUK/status/1206320645992267777", "retweet": false, "quote_url": "", "video": 0, "thumbnail": "", "near": "", "geo": "54.153709,-4.529766,527km", "source": "", "user_rt_id": "", "user_rt": "", "retweet_id": "", "reply_to": [], "retweet_date": "", "translate": "", "trans_src": "", "trans_dest": ""}
{"id": 1206320623229849600, "conversation_id": "1206320623229849600", "created_at": "2019-12-15 21:10:23 GMT", "date": "2019-12-15", "time": "21:10:23", "timezone": "+0000", "user_id": 3446146816, "username": "riverlevelsuk", "name": "River Levels UK", "place": {"type": "Point", "coordinates": [51.193675, -2.826568]}, "tweet": "Flood Alert: East Somerset Rivers 20:57 15 December  https://t.co/48reADpMUR", "language": "en", "mentions": [], "urls": ["https://riverlevels.uk/flood-warning-east-somerset-rivers/1576444223"], "photos": [], "replies_count": 0, "retweets_count": 0, "likes_count": 0, "hashtags": [], "cashtags": [], "link": "https://twitter.com/RiverlevelsUK/status/1206320623229849600", "retweet": false, "quote_url": "", "video": 0, "thumbnail": "", "near": "", "geo": "54.153709,-4.529766,527km", "source": "", "user_rt_id": "", "user_rt": "", "retweet_id": "", "reply_to": [], "retweet_date": "", "translate": "", "trans_src": "", "trans_dest": ""}
{"id": 1206320600421150722, "conversation_id": "1206320600421150722", "created_at": "2019-12-15 21:10:18 GMT", "date": "2019-12-15", "time": "21:10:18", "timezone": "+0000", "user_id": 3446146816, "username": "riverlevelsuk", "name": "River Levels UK", "place": {"type": "Point", "coordinates": [52.355557, -0.304837]}, "tweet": "Flood Alert: Alconbury Brook and Ellington Brook in Cambridgeshire 20:46 15 December  https://t.co/xfEkkFVGpN", "language": "en", "mentions": [], "urls": ["https://riverlevels.uk/flood-warning-alconbury-and-ellington-brooks/1576444217"], "photos": [], "replies_count": 0, "retweets_count": 0, "likes_count": 0, "hashtags": [], "cashtags": [], "link": "https://twitter.com/RiverlevelsUK/status/1206320600421150722", "retweet": false, "quote_url": "", "video": 0, "thumbnail": "", "near": "", "geo": "54.153709,-4.529766,527km", "source": "", "user_rt_id": "", "user_rt": "", "retweet_id": "", "reply_to": [], "retweet_date": "", "translate": "", "trans_src": "", "trans_dest": ""}
{"id": 1206320195654033408, "conversation_id": "1206320195654033408", "created_at": "2019-12-15 21:08:41 GMT", "date": "2019-12-15", "time": "21:08:41", "timezone": "+0000", "user_id": 510251287, "username": "uddens", "name": "Cannon Hill Friends", "place": {"type": "Point", "coordinates": [50.807725, -1.9000098]}, "tweet": "A wet walk in Uddens today. Uddens Water had burst her banks flooding sections of the Castleman Trailway. Was able to avoid the worst of it and only got slightly wet feet 💦😏 Great to see so many people out and…  https://t.co/NNOMELPmcl", "language": "en", "mentions": [], "urls": ["https://www.instagram.com/p/B6G4xASDSxt/?igshid=c6idtgdqbs5k"], "photos": [], "replies_count": 0, "retweets_count": 1, "likes_count": 3, "hashtags": [], "cashtags": [], "link": "https://twitter.com/Uddens/status/1206320195654033408", "retweet": false, "quote_url": "", "video": 0, "thumbnail": "", "near": "", "geo": "54.153709,-4.529766,527km", "source": "", "user_rt_id": "", "user_rt": "", "retweet_id": "", "reply_to": [], "retweet_date": "", "translate": "", "trans_src": "", "trans_dest": ""}
{"id": 1206318107352064000, "conversation_id": "1206318107352064000", "created_at": "2019-12-15 21:00:23 GMT", "date": "2019-12-15", "time": "21:00:23", "timezone": "+0000", "user_id": 3446146816, "username": "riverlevelsuk", "name": "River Levels UK", "place": {"type": "Point", "coordinates": [51.010791, -3.221625]}, "tweet": "Flood Alert: River Tone Catchment 20:38 15 December  https://t.co/eZX8l9JAUC", "language": "en", "mentions": [], "urls": ["https://riverlevels.uk/flood-warning-river-tone-catchment/1576443623"], "photos": [], "replies_count": 0, "retweets_count": 0, "likes_count": 0, "hashtags": [], "cashtags": [], "link": "https://twitter.com/RiverlevelsUK/status/1206318107352064000", "retweet": false, "quote_url": "", "video": 0, "thumbnail": "", "near": "", "geo": "54.153709,-4.529766,527km", "source": "", "user_rt_id": "", "user_rt": "", "retweet_id": "", "reply_to": [], "retweet_date": "", "translate": "", "trans_src": "", "trans_dest": ""}
{"id": 1206318084518285312, "conversation_id": "1206318084518285312", "created_at": "2019-12-15 21:00:18 GMT", "date": "2019-12-15", "time": "21:00:18", "timezone": "+0000", "user_id": 3446146816, "username": "riverlevelsuk", "name": "River Levels UK", "place": {"type": "Point", "coordinates": [52.370664, -2.88566]}, "tweet": "Flood Alert: Upper Teme 20:37 15 December  https://t.co/QfYe6uQmfj", "language": "en", "mentions": [], "urls": ["https://riverlevels.uk/flood-warning-upper-teme/1576443618"], "photos": [], "replies_count": 0, "retweets_count": 0, "likes_count": 0, "hashtags": [], "cashtags": [], "link": "https://twitter.com/RiverlevelsUK/status/1206318084518285312", "retweet": false, "quote_url": "", "video": 0, "thumbnail": "", "near": "", "geo": "54.153709,-4.529766,527km", "source": "", "user_rt_id": "", "user_rt": "", "retweet_id": "", "reply_to": [], "retweet_date": "", "translate": "", "trans_src": "", "trans_dest": ""}
{"id": 1206315766649380865, "conversation_id": "1206315766649380865", "created_at": "2019-12-15 20:51:05 GMT", "date": "2019-12-15", "time": "20:51:05", "timezone": "+0000", "user_id": 3446146816, "username": "riverlevelsuk", "name": "River Levels UK", "place": {"type": "Point", "coordinates": [52.138998, -2.222087]}, "tweet": "Flood Alert: Kempsey Village 20:27 15 December  https://t.co/bURiSaxQ2u", "language": "en", "mentions": [], "urls": ["https://riverlevels.uk/flood-warning-kempsey-village/1576443065"], "photos": [], "replies_count": 0, "retweets_count": 0, "likes_count": 0, "hashtags": [], "cashtags": [], "link": "https://twitter.com/RiverlevelsUK/status/1206315766649380865", "retweet": false, "quote_url": "", "video": 0, "thumbnail": "", "near": "", "geo": "54.153709,-4.529766,527km", "source": "", "user_rt_id": "", "user_rt": "", "retweet_id": "", "reply_to": [], "retweet_date": "", "translate": "", "trans_src": "", "trans_dest": ""}
{"id": 1206315743962423296, "conversation_id": "1206315743962423296", "created_at": "2019-12-15 20:51:00 GMT", "date": "2019-12-15", "time": "20:51:00", "timezone": "+0000", "user_id": 3446146816, "username": "riverlevelsuk", "name": "River Levels UK", "place": {"type": "Point", "coordinates": [50.649943, -2.485343]}, "tweet": "Flood Alert: Weymouth Rivers and Streams 20:25 15 December  https://t.co/ythe6IeLkg", "language": "en", "mentions": [], "urls": ["https://riverlevels.uk/flood-warning-weymouth-rivers-and-streams/1576443059"], "photos": [], "replies_count": 0, "retweets_count": 0, "likes_count": 0, "hashtags": [], "cashtags": [], "link": "https://twitter.com/RiverlevelsUK/status/1206315743962423296", "retweet": false, "quote_url": "", "video": 0, "thumbnail": "", "near": "", "geo": "54.153709,-4.529766,527km", "source": "", "user_rt_id": "", "user_rt": "", "retweet_id": "", "reply_to": [], "retweet_date": "", "translate": "", "trans_src": "", "trans_dest": ""}
{"id": 1206315721233485825, "conversation_id": "1206315721233485825", "created_at": "2019-12-15 20:50:54 GMT", "date": "2019-12-15", "time": "20:50:54", "timezone": "+0000", "user_id": 3446146816, "username": "riverlevelsuk", "name": "River Levels UK", "place": {"type": "Point", "coordinates": [51.939637, -2.216366]}, "tweet": "Flood Alert: River Severn in Gloucestershire 20:24 15 December  https://t.co/DscT82gOEC", "language": "en", "mentions": [], "urls": ["https://riverlevels.uk/flood-warning-river-severn-in-gloucestershire/1576443054"], "photos": [], "replies_count": 0, "retweets_count": 0, "likes_count": 0, "hashtags": [], "cashtags": [], "link": "https://twitter.com/RiverlevelsUK/status/1206315721233485825", "retweet": false, "quote_url": "", "video": 0, "thumbnail": "", "near": "", "geo": "54.153709,-4.529766,527km", "source": "", "user_rt_id": "", "user_rt": "", "retweet_id": "", "reply_to": [], "retweet_date": "", "translate": "", "trans_src": "", "trans_dest": ""}
{"id": 1206315698416476160, "conversation_id": "1206315698416476160", "created_at": "2019-12-15 20:50:49 GMT", "date": "2019-12-15", "time": "20:50:49", "timezone": "+0000", "user_id": 3446146816, "username": "riverlevelsuk", "name": "River Levels UK", "place": {"type": "Point", "coordinates": [52.173346, -2.239888]}, "tweet": "Flood Alert: River Severn in Worcestershire 20:27 15 December  https://t.co/MBAowr18Ql", "language": "en", "mentions": [], "urls": ["https://riverlevels.uk/flood-warning-river-severn-in-worcestershire/1576443049"], "photos": [], "replies_count": 0, "retweets_count": 0, "likes_count": 0, "hashtags": [], "cashtags": [], "link": "https://twitter.com/RiverlevelsUK/status/1206315698416476160", "retweet": false, "quote_url": "", "video": 0, "thumbnail": "", "near": "", "geo": "54.153709,-4.529766,527km", "source": "", "user_rt_id": "", "user_rt": "", "retweet_id": "", "reply_to": [], "retweet_date": "", "translate": "", "trans_src": "", "trans_dest": ""}
{"id": 1206315675695898627, "conversation_id": "1206315675695898627", "created_at": "2019-12-15 20:50:44 GMT", "date": "2019-12-15", "time": "20:50:44", "timezone": "+0000", "user_id": 3446146816, "username": "riverlevelsuk", "name": "River Levels UK", "place": {"type": "Point", "coordinates": [52.088367, -2.098589]}, "tweet": "Flood Alert: River Avon in Worcestershire 20:26 15 December  https://t.co/HV9hWehxyA", "language": "en", "mentions": [], "urls": ["https://riverlevels.uk/flood-warning-river-avon-in-worcestershire/1576443043"], "photos": [], "replies_count": 0, "retweets_count": 0, "likes_count": 0, "hashtags": [], "cashtags": [], "link": "https://twitter.com/RiverlevelsUK/status/1206315675695898627", "retweet": false, "quote_url": "", "video": 0, "thumbnail": "", "near": "", "geo": "54.153709,-4.529766,527km", "source": "", "user_rt_id": "", "user_rt": "", "retweet_id": "", "reply_to": [], "retweet_date": "", "translate": "", "trans_src": "", "trans_dest": ""}
{"id": 1206315646537125888, "conversation_id": "1206315646537125888", "created_at": "2019-12-15 20:50:37 GMT", "date": "2019-12-15", "time": "20:50:37", "timezone": "+0000", "user_id": 3446146816, "username": "riverlevelsuk", "name": "River Levels UK", "place": {"type": "Point", "coordinates": [51.962777, -2.372382]}, "tweet": "Flood Alert: River Leadon Catchment 20:24 15 December  https://t.co/XUnQRYkuFt", "language": "en", "mentions": [], "urls": ["https://riverlevels.uk/flood-warning-river-leadon-catchment/1576443036"], "photos": [], "replies_count": 0, "retweets_count": 0, "likes_count": 0, "hashtags": [], "cashtags": [], "link": "https://twitter.com/RiverlevelsUK/status/1206315646537125888", "retweet": false, "quote_url": "", "video": 0, "thumbnail": "", "near": "", "geo": "54.153709,-4.529766,527km", "source": "", "user_rt_id": "", "user_rt": "", "retweet_id": "", "reply_to": [], "retweet_date": "", "translate": "", "trans_src": "", "trans_dest": ""}
{"id": 1206315623904616454, "conversation_id": "1206315623904616454", "created_at": "2019-12-15 20:50:31 GMT", "date": "2019-12-15", "time": "20:50:31", "timezone": "+0000", "user_id": 3446146816, "username": "riverlevelsuk", "name": "River Levels UK", "place": {"type": "Point", "coordinates": [52.212204, -2.070642]}, "tweet": "Flood Alert: Bow and Piddle Brook 20:26 15 December  https://t.co/RSOS5NmKaR", "language": "en", "mentions": [], "urls": ["https://riverlevels.uk/flood-warning-bow-and-piddle-brook/1576443031"], "photos": [], "replies_count": 0, "retweets_count": 0, "likes_count": 0, "hashtags": [], "cashtags": [], "link": "https://twitter.com/RiverlevelsUK/status/1206315623904616454", "retweet": false, "quote_url": "", "video": 0, "thumbnail": "", "near": "", "geo": "54.153709,-4.529766,527km", "source": "", "user_rt_id": "", "user_rt": "", "retweet_id": "", "reply_to": [], "retweet_date": "", "translate": "", "trans_src": "", "trans_dest": ""}
{"id": 1206315601154756608, "conversation_id": "1206315601154756608", "created_at": "2019-12-15 20:50:26 GMT", "date": "2019-12-15", "time": "20:50:26", "timezone": "+0000", "user_id": 3446146816, "username": "riverlevelsuk", "name": "River Levels UK", "place": {"type": "Point", "coordinates": [51.99374, -2.169121]}, "tweet": "Flood Warning: River Severn at Severn Ham, Tewkesbury 20:24 15 December  https://t.co/Ju7LTnJubG", "language": "en", "mentions": [], "urls": ["https://riverlevels.uk/flood-warning-river-severn-at-severn-ham-tewkesbury/1576443025"], "photos": [], "replies_count": 0, "retweets_count": 0, "likes_count": 0, "hashtags": [], "cashtags": [], "link": "https://twitter.com/RiverlevelsUK/status/1206315601154756608", "retweet": false, "quote_url": "", "video": 0, "thumbnail": "", "near": "", "geo": "54.153709,-4.529766,527km", "source": "", "user_rt_id": "", "user_rt": "", "retweet_id": "", "reply_to": [], "retweet_date": "", "translate": "", "trans_src": "", "trans_dest": ""}
{"id": 1206315578396495873, "conversation_id": "1206315578396495873", "created_at": "2019-12-15 20:50:20 GMT", "date": "2019-12-15", "time": "20:50:20", "timezone": "+0000", "user_id": 3446146816, "username": "riverlevelsuk", "name": "River Levels UK", "place": {"type": "Point", "coordinates": [51.93953, -2.196688]}, "tweet": "Flood Warning: River Severn at Apperley and The Leigh 20:24 15 December  https://t.co/QwGlbfeZnF", "language": "en", "mentions": [], "urls": ["https://riverlevels.uk/flood-warning-river-severn-at-apperley-and-the-leigh/1576443020"], "photos": [], "replies_count": 0, "retweets_count": 0, "likes_count": 0, "hashtags": [], "cashtags": [], "link": "https://twitter.com/RiverlevelsUK/status/1206315578396495873", "retweet": false, "quote_url": "", "video": 0, "thumbnail": "", "near": "", "geo": "54.153709,-4.529766,527km", "source": "", "user_rt_id": "", "user_rt": "", "retweet_id": "", "reply_to": [], "retweet_date": "", "translate": "", "trans_src": "", "trans_dest": ""}
{"id": 1206315555633999872, "conversation_id": "1206315555633999872", "created_at": "2019-12-15 20:50:15 GMT", "date": "2019-12-15", "time": "20:50:15", "timezone": "+0000", "user_id": 3446146816, "username": "riverlevelsuk", "name": "River Levels UK", "place": {"type": "Point", "coordinates": [52.148259, -2.227994]}, "tweet": "Flood Warning: River Severn at Court Meadow, Kempsey and Callow End 20:25 15 December  https://t.co/qlX0xFADL5", "language": "en", "mentions": [], "urls": ["https://riverlevels.uk/flood-warning-river-severn-at-court-meadow-kempsey-and-callow-end/1576443015"], "photos": [], "replies_count": 0, "retweets_count": 0, "likes_count": 0, "hashtags": [], "cashtags": [], "link": "https://twitter.com/RiverlevelsUK/status/1206315555633999872", "retweet": false, "quote_url": "", "video": 0, "thumbnail": "", "near": "", "geo": "54.153709,-4.529766,527km", "source": "", "user_rt_id": "", "user_rt": "", "retweet_id": "", "reply_to": [], "retweet_date": "", "translate": "", "trans_src": "", "trans_dest": ""}
{"id": 1206312549760819200, "conversation_id": "1206312549760819200", "created_at": "2019-12-15 20:38:18 GMT", "date": "2019-12-15", "time": "20:38:18", "timezone": "+0000", "user_id": 964145767169642496, "username": "emma_lfc89", "name": "💙⭐⭐⭐Emzy⭐⭐⭐💙", "place": "", "tweet": "So many memories came flooding back  https://t.co/slqCPIgdFF", "language": "en", "mentions": [], "urls": [], "photos": [], "replies_count": 0, "retweets_count": 0, "likes_count": 3, "hashtags": [], "cashtags": [], "link": "https://twitter.com/Emma_LFC89/status/1206312549760819200", "retweet": false, "quote_url": "", "video": 1, "thumbnail": "https://pbs.twimg.com/ext_tw_video_thumb/1206311652653707264/pu/img/6MirQjhr_vQiEn70.jpg", "near": "", "geo": "54.153709,-4.529766,527km", "source": "", "user_rt_id": "", "user_rt": "", "retweet_id": "", "reply_to": [], "retweet_date": "", "translate": "", "trans_src": "", "trans_dest": ""}
{"id": 1206310693051518976, "conversation_id": "1206310693051518976", "created_at": "2019-12-15 20:30:56 GMT", "date": "2019-12-15", "time": "20:30:56", "timezone": "+0000", "user_id": 3446146816, "username": "riverlevelsuk", "name": "River Levels UK", "place": {"type": "Point", "coordinates": [51.402516, -0.543822]}, "tweet": "Flood Alert: Chertsey Bourne 20:06 15 December  https://t.co/pXTri7Zt9p", "language": "en", "mentions": [], "urls": ["https://riverlevels.uk/flood-warning-chertsey-bourne/1576441855"], "photos": [], "replies_count": 0, "retweets_count": 0, "likes_count": 0, "hashtags": [], "cashtags": [], "link": "https://twitter.com/RiverlevelsUK/status/1206310693051518976", "retweet": false, "quote_url": "", "video": 0, "thumbnail": "", "near": "", "geo": "54.153709,-4.529766,527km", "source": "", "user_rt_id": "", "user_rt": "", "retweet_id": "", "reply_to": [], "retweet_date": "", "translate": "", "trans_src": "", "trans_dest": ""}
{"id": 1206310670297444353, "conversation_id": "1206310670297444353", "created_at": "2019-12-15 20:30:50 GMT", "date": "2019-12-15", "time": "20:30:50", "timezone": "+0000", "user_id": 3446146816, "username": "riverlevelsuk", "name": "River Levels UK", "place": {"type": "Point", "coordinates": [51.488069, -0.882146]}, "tweet": "Flood Alert: Lower River Loddon at the River Thames confluence at Twyford 20:04 15 December  https://t.co/31ff43Ps5e", "language": "en", "mentions": [], "urls": ["https://riverlevels.uk/flood-warning-lower-river-loddon-at-the-river-thames-confluence-at-twyford/1576441850"], "photos": [], "replies_count": 0, "retweets_count": 0, "likes_count": 0, "hashtags": [], "cashtags": [], "link": "https://twitter.com/RiverlevelsUK/status/1206310670297444353", "retweet": false, "quote_url": "", "video": 0, "thumbnail": "", "near": "", "geo": "54.153709,-4.529766,527km", "source": "", "user_rt_id": "", "user_rt": "", "retweet_id": "", "reply_to": [], "retweet_date": "", "translate": "", "trans_src": "", "trans_dest": ""}
{"id": 1206310624730501120, "conversation_id": "1206310624730501120", "created_at": "2019-12-15 20:30:39 GMT", "date": "2019-12-15", "time": "20:30:39", "timezone": "+0000", "user_id": 3446146816, "username": "riverlevelsuk", "name": "River Levels UK", "place": {"type": "Point", "coordinates": [51.558923, -0.747914]}, "tweet": "Flood Alert: River Thames from Hurley to Cookham 20:05 15 December  https://t.co/WXjDGbgyPk", "language": "en", "mentions": [], "urls": ["https://riverlevels.uk/flood-warning-river-thames-from-hurley-to-cookham/1576441839"], "photos": [], "replies_count": 0, "retweets_count": 0, "likes_count": 0, "hashtags": [], "cashtags": [], "link": "https://twitter.com/RiverlevelsUK/status/1206310624730501120", "retweet": false, "quote_url": "", "video": 0, "thumbnail": "", "near": "", "geo": "54.153709,-4.529766,527km", "source": "", "user_rt_id": "", "user_rt": "", "retweet_id": "", "reply_to": [], "retweet_date": "", "translate": "", "trans_src": "", "trans_dest": ""}
{"id": 1206310556468236288, "conversation_id": "1206310556468236288", "created_at": "2019-12-15 20:30:23 GMT", "date": "2019-12-15", "time": "20:30:23", "timezone": "+0000", "user_id": 3446146816, "username": "riverlevelsuk", "name": "River Levels UK", "place": {"type": "Point", "coordinates": [51.338927, -0.816868]}, "tweet": "Flood Alert: River Blackwater and The Cove Brook 20:05 15 December  https://t.co/m0M1mvkp1S", "language": "en", "mentions": [], "urls": ["https://riverlevels.uk/flood-warning-river-blackwater-and-the-cove-brook/1576441823"], "photos": [], "replies_count": 0, "retweets_count": 0, "likes_count": 0, "hashtags": [], "cashtags": [], "link": "https://twitter.com/RiverlevelsUK/status/1206310556468236288", "retweet": false, "quote_url": "", "video": 0, "thumbnail": "", "near": "", "geo": "54.153709,-4.529766,527km", "source": "", "user_rt_id": "", "user_rt": "", "retweet_id": "", "reply_to": [], "retweet_date": "", "translate": "", "trans_src": "", "trans_dest": ""}
{"id": 1206308704838131717, "conversation_id": "1206281097564299271", "created_at": "2019-12-15 20:23:02 GMT", "date": "2019-12-15", "time": "20:23:02", "timezone": "+0000", "user_id": 858177372, "username": "petagna", "name": "Marco Petagna", "place": "", "tweet": "@deanhall30 @metoffice Lots of flooding coming into work😲", "language": "en", "mentions": [], "urls": [], "photos": [], "replies_count": 0, "retweets_count": 0, "likes_count": 1, "hashtags": [], "cashtags": [], "link": "https://twitter.com/Petagna/status/1206308704838131717", "retweet": false, "quote_url": "", "video": 0, "thumbnail": "", "near": "", "geo": "54.153709,-4.529766,527km", "source": "", "user_rt_id": "", "user_rt": "", "retweet_id": "", "reply_to": [{"screen_name": "deanhall30", "name": "Dean Hall", "id": "2473598039"}, {"screen_name": "metoffice", "name": "Met Office", "id": "19282280"}], "retweet_date": "", "translate": "", "trans_src": "", "trans_dest": ""}
{"id": 1206308021216915456, "conversation_id": "1206308021216915456", "created_at": "2019-12-15 20:20:19 GMT", "date": "2019-12-15", "time": "20:20:19", "timezone": "+0000", "user_id": 3446146816, "username": "riverlevelsuk", "name": "River Levels UK", "place": {"type": "Point", "coordinates": [52.026346, -0.947197]}, "tweet": "Flood Alert: Upper River Great Ouse in Northamptonshire, Oxfordshire and Buckinghamshire 19:35 15 December  https://t.co/gt68hUZXGi", "language": "en", "mentions": [], "urls": ["https://riverlevels.uk/flood-warning-upper-river-great-ouse-in-northamptonshire-oxfordshire-and-buckinghamshire/1576441218"], "photos": [], "replies_count": 0, "retweets_count": 0, "likes_count": 0, "hashtags": [], "cashtags": [], "link": "https://twitter.com/RiverlevelsUK/status/1206308021216915456", "retweet": false, "quote_url": "", "video": 0, "thumbnail": "", "near": "", "geo": "54.153709,-4.529766,527km", "source": "", "user_rt_id": "", "user_rt": "", "retweet_id": "", "reply_to": [], "retweet_date": "", "translate": "", "trans_src": "", "trans_dest": ""}
{"id": 1206307998341193744, "conversation_id": "1206307998341193744", "created_at": "2019-12-15 20:20:13 GMT", "date": "2019-12-15", "time": "20:20:13", "timezone": "+0000", "user_id": 3446146816, "username": "riverlevelsuk", "name": "River Levels UK", "place": {"type": "Point", "coordinates": [52.119002, -0.959968]}, "tweet": "Flood Alert: River Tove in Northamptonshire 19:35 15 December  https://t.co/92aIWLM4cj", "language": "en", "mentions": [], "urls": ["https://riverlevels.uk/flood-warning-river-tove-in-northamptonshire/1576441213"], "photos": [], "replies_count": 0, "retweets_count": 0, "likes_count": 0, "hashtags": [], "cashtags": [], "link": "https://twitter.com/RiverlevelsUK/status/1206307998341193744", "retweet": false, "quote_url": "", "video": 0, "thumbnail": "", "near": "", "geo": "54.153709,-4.529766,527km", "source": "", "user_rt_id": "", "user_rt": "", "retweet_id": "", "reply_to": [], "retweet_date": "", "translate": "", "trans_src": "", "trans_dest": ""}
{"id": 1206306608747368452, "conversation_id": "1206306608747368452", "created_at": "2019-12-15 20:14:42 GMT", "date": "2019-12-15", "time": "20:14:42", "timezone": "+0000", "user_id": 2217403956, "username": "stuckinarock", "name": "#stuckinarock", "place": "", "tweet": "Interesting site on the Little Park area of Crane - took a long time but my wife and I eventually decided it was wooden not dead! @FriendsRivCrane @LBRUT heavy flooding along route and the furrows impassable @Whittonvillage  https://t.co/2DOja1OiOp", "language": "en", "mentions": [{"screen_name": "friendsrivcrane", "name": "force", "id": "470403220"}, {"screen_name": "lbrut", "name": "richmond council", "id": "84105845"}, {"screen_name": "whittonvillage", "name": "whitton village", "id": "540266686"}], "urls": [], "photos": ["https://pbs.twimg.com/media/EL2pdiLX0AEazfW.jpg"], "replies_count": 0, "retweets_count": 0, "likes_count": 0, "hashtags": [], "cashtags": [], "link": "https://twitter.com/Stuckinarock/status/1206306608747368452", "retweet": false, "quote_url": "", "video": 1, "thumbnail": "https://pbs.twimg.com/media/EL2pdiLX0AEazfW.jpg", "near": "", "geo": "54.153709,-4.529766,527km", "source": "", "user_rt_id": "", "user_rt": "", "retweet_id": "", "reply_to": [], "retweet_date": "", "translate": "", "trans_src": "", "trans_dest": ""}
{"id": 1206305706145714176, "conversation_id": "1206305706145714176", "created_at": "2019-12-15 20:11:07 GMT", "date": "2019-12-15", "time": "20:11:07", "timezone": "+0000", "user_id": 3446146816, "username": "riverlevelsuk", "name": "River Levels UK", "place": {"type": "Point", "coordinates": [52.142726, -0.54902]}, "tweet": "Flood Alert: Middle River Great Ouse in Milton Keynes, Bedford Borough and Central Bedfordshire 19:35 15 December  https://t.co/AUNjkvtJ4S", "language": "en", "mentions": [], "urls": ["https://riverlevels.uk/flood-warning-middle-river-great-ouse-in-milton-keynes-bedford-borough-and-central-bedfordshire/1576440666"], "photos": [], "replies_count": 0, "retweets_count": 0, "likes_count": 0, "hashtags": [], "cashtags": [], "link": "https://twitter.com/RiverlevelsUK/status/1206305706145714176", "retweet": false, "quote_url": "", "video": 0, "thumbnail": "", "near": "", "geo": "54.153709,-4.529766,527km", "source": "", "user_rt_id": "", "user_rt": "", "retweet_id": "", "reply_to": [], "retweet_date": "", "translate": "", "trans_src": "", "trans_dest": ""}
{"id": 1206305683353853953, "conversation_id": "1206305683353853953", "created_at": "2019-12-15 20:11:01 GMT", "date": "2019-12-15", "time": "20:11:01", "timezone": "+0000", "user_id": 3446146816, "username": "riverlevelsuk", "name": "River Levels UK", "place": {"type": "Point", "coordinates": [50.913481, -2.58627]}, "tweet": "Flood Alert: South East Somerset Rivers, Upper Reaches 19:31 15 December  https://t.co/vF6RKaqlhx", "language": "en", "mentions": [], "urls": ["https://riverlevels.uk/flood-warning-south-east-somerset-rivers-upper-reaches/1576440661"], "photos": [], "replies_count": 0, "retweets_count": 0, "likes_count": 0, "hashtags": [], "cashtags": [], "link": "https://twitter.com/RiverlevelsUK/status/1206305683353853953", "retweet": false, "quote_url": "", "video": 0, "thumbnail": "", "near": "", "geo": "54.153709,-4.529766,527km", "source": "", "user_rt_id": "", "user_rt": "", "retweet_id": "", "reply_to": [], "retweet_date": "", "translate": "", "trans_src": "", "trans_dest": ""}
{"id": 1206305660608155649, "conversation_id": "1206305660608155649", "created_at": "2019-12-15 20:10:56 GMT", "date": "2019-12-15", "time": "20:10:56", "timezone": "+0000", "user_id": 3446146816, "username": "riverlevelsuk", "name": "River Levels UK", "place": {"type": "Point", "coordinates": [51.062699, -2.960397]}, "tweet": "Flood Alert: Lower Tone and Parrett Moors 19:35 15 December  https://t.co/TRHMmrFwvD", "language": "en", "mentions": [], "urls": ["https://riverlevels.uk/flood-warning-lower-tone-and-parrett-moors/1576440655"], "photos": [], "replies_count": 0, "retweets_count": 0, "likes_count": 0, "hashtags": [], "cashtags": [], "link": "https://twitter.com/RiverlevelsUK/status/1206305660608155649", "retweet": false, "quote_url": "", "video": 0, "thumbnail": "", "near": "", "geo": "54.153709,-4.529766,527km", "source": "", "user_rt_id": "", "user_rt": "", "retweet_id": "", "reply_to": [], "retweet_date": "", "translate": "", "trans_src": "", "trans_dest": ""}
{"id": 1206305637531111424, "conversation_id": "1206305637531111424", "created_at": "2019-12-15 20:10:50 GMT", "date": "2019-12-15", "time": "20:10:50", "timezone": "+0000", "user_id": 3446146816, "username": "riverlevelsuk", "name": "River Levels UK", "place": {"type": "Point", "coordinates": [51.853542, -1.118554]}, "tweet": "Flood Alert: River Ray and its tributaries from Shipton Lee to and including Islip 19:44 15 December  https://t.co/s9pnORlhbF", "language": "en", "mentions": [], "urls": ["https://riverlevels.uk/flood-warning-river-ray-and-its-tributaries-from-shipton-lee-to-and-including-islip/1576440650"], "photos": [], "replies_count": 0, "retweets_count": 0, "likes_count": 0, "hashtags": [], "cashtags": [], "link": "https://twitter.com/RiverlevelsUK/status/1206305637531111424", "retweet": false, "quote_url": "", "video": 0, "thumbnail": "", "near": "", "geo": "54.153709,-4.529766,527km", "source": "", "user_rt_id": "", "user_rt": "", "retweet_id": "", "reply_to": [], "retweet_date": "", "translate": "", "trans_src": "", "trans_dest": ""}
{"id": 1206305614911156226, "conversation_id": "1206305614911156226", "created_at": "2019-12-15 20:10:45 GMT", "date": "2019-12-15", "time": "20:10:45", "timezone": "+0000", "user_id": 3446146816, "username": "riverlevelsuk", "name": "River Levels UK", "place": {"type": "Point", "coordinates": [51.763206, -0.974615]}, "tweet": "Flood Alert: River Thame and Chalgrove Brook 19:44 15 December  https://t.co/sxcPHea4sj", "language": "en", "mentions": [], "urls": ["https://riverlevels.uk/flood-warning-river-thame-and-chalgrove-brook/1576440645"], "photos": [], "replies_count": 0, "retweets_count": 0, "likes_count": 0, "hashtags": [], "cashtags": [], "link": "https://twitter.com/RiverlevelsUK/status/1206305614911156226", "retweet": false, "quote_url": "", "video": 0, "thumbnail": "", "near": "", "geo": "54.153709,-4.529766,527km", "source": "", "user_rt_id": "", "user_rt": "", "retweet_id": "", "reply_to": [], "retweet_date": "", "translate": "", "trans_src": "", "trans_dest": ""}
{"id": 1206305591297220619, "conversation_id": "1206305591297220619", "created_at": "2019-12-15 20:10:39 GMT", "date": "2019-12-15", "time": "20:10:39", "timezone": "+0000", "user_id": 3446146816, "username": "riverlevelsuk", "name": "River Levels UK", "place": {"type": "Point", "coordinates": [51.662357, -1.77349]}, "tweet": "Flood Alert: River Thames and its small tributaries from Calcutt to Lechlade 19:44 15 December  https://t.co/G0zaoeh5qo", "language": "en", "mentions": [], "urls": ["https://riverlevels.uk/flood-warning-river-thames-and-its-small-tributaries-from-calcutt-to-lechlade/1576440639"], "photos": [], "replies_count": 0, "retweets_count": 0, "likes_count": 0, "hashtags": [], "cashtags": [], "link": "https://twitter.com/RiverlevelsUK/status/1206305591297220619", "retweet": false, "quote_url": "", "video": 0, "thumbnail": "", "near": "", "geo": "54.153709,-4.529766,527km", "source": "", "user_rt_id": "", "user_rt": "", "retweet_id": "", "reply_to": [], "retweet_date": "", "translate": "", "trans_src": "", "trans_dest": ""}
{"id": 1206305568639590401, "conversation_id": "1206305568639590401", "created_at": "2019-12-15 20:10:34 GMT", "date": "2019-12-15", "time": "20:10:34", "timezone": "+0000", "user_id": 3446146816, "username": "riverlevelsuk", "name": "River Levels UK", "place": {"type": "Point", "coordinates": [51.722692, -1.481323]}, "tweet": "Flood Alert: River Thames and tributaries from Buscot Wick down to Kings Lock 19:48 15 December  https://t.co/U8ryRWrS0u", "language": "en", "mentions": [], "urls": ["https://riverlevels.uk/flood-warning-the-river-thames-and-tributaries-from-buscot-wick-down-to-kings-lock/1576440634"], "photos": [], "replies_count": 0, "retweets_count": 0, "likes_count": 0, "hashtags": [], "cashtags": [], "link": "https://twitter.com/RiverlevelsUK/status/1206305568639590401", "retweet": false, "quote_url": "", "video": 0, "thumbnail": "", "near": "", "geo": "54.153709,-4.529766,527km", "source": "", "user_rt_id": "", "user_rt": "", "retweet_id": "", "reply_to": [], "retweet_date": "", "translate": "", "trans_src": "", "trans_dest": ""}
{"id": 1206305545973616642, "conversation_id": "1206305545973616642", "created_at": "2019-12-15 20:10:28 GMT", "date": "2019-12-15", "time": "20:10:28", "timezone": "+0000", "user_id": 3446146816, "username": "riverlevelsuk", "name": "River Levels UK", "place": {"type": "Point", "coordinates": [51.828598, -1.65286]}, "tweet": "Flood Alert: River Windrush from Bourton to Newbridge 19:44 15 December  https://t.co/bN3OWc4F56", "language": "en", "mentions": [], "urls": ["https://riverlevels.uk/flood-warning-river-windrush-from-bourton-to-newbridge/1576440628"], "photos": [], "replies_count": 0, "retweets_count": 0, "likes_count": 0, "hashtags": [], "cashtags": [], "link": "https://twitter.com/RiverlevelsUK/status/1206305545973616642", "retweet": false, "quote_url": "", "video": 0, "thumbnail": "", "near": "", "geo": "54.153709,-4.529766,527km", "source": "", "user_rt_id": "", "user_rt": "", "retweet_id": "", "reply_to": [], "retweet_date": "", "translate": "", "trans_src": "", "trans_dest": ""}
{"id": 1206305523274002432, "conversation_id": "1206305523274002432", "created_at": "2019-12-15 20:10:23 GMT", "date": "2019-12-15", "time": "20:10:23", "timezone": "+0000", "user_id": 3446146816, "username": "riverlevelsuk", "name": "River Levels UK", "place": {"type": "Point", "coordinates": [51.898998, -1.746441]}, "tweet": "Flood Alert: River Dikler from Condicote to Little Rissington 19:44 15 December  https://t.co/2xLC0C227d", "language": "en", "mentions": [], "urls": ["https://riverlevels.uk/flood-warning-river-dikler-from-condicote-to-little-rissington/1576440623"], "photos": [], "replies_count": 0, "retweets_count": 0, "likes_count": 0, "hashtags": [], "cashtags": [], "link": "https://twitter.com/RiverlevelsUK/status/1206305523274002432", "retweet": false, "quote_url": "", "video": 0, "thumbnail": "", "near": "", "geo": "54.153709,-4.529766,527km", "source": "", "user_rt_id": "", "user_rt": "", "retweet_id": "", "reply_to": [], "retweet_date": "", "translate": "", "trans_src": "", "trans_dest": ""}
{"id": 1206305500524142597, "conversation_id": "1206305500524142597", "created_at": "2019-12-15 20:10:18 GMT", "date": "2019-12-15", "time": "20:10:18", "timezone": "+0000", "user_id": 3446146816, "username": "riverlevelsuk", "name": "River Levels UK", "place": {"type": "Point", "coordinates": [51.288357, -0.591994]}, "tweet": "Flood Alert: Hoe Stream 19:53 15 December  https://t.co/czdLmlBZM3", "language": "en", "mentions": [], "urls": ["https://riverlevels.uk/flood-warning-hoe-stream/1576440617"], "photos": [], "replies_count": 0, "retweets_count": 0, "likes_count": 0, "hashtags": [], "cashtags": [], "link": "https://twitter.com/RiverlevelsUK/status/1206305500524142597", "retweet": false, "quote_url": "", "video": 0, "thumbnail": "", "near": "", "geo": "54.153709,-4.529766,527km", "source": "", "user_rt_id": "", "user_rt": "", "retweet_id": "", "reply_to": [], "retweet_date": "", "translate": "", "trans_src": "", "trans_dest": ""}
{"id": 1206304895957176320, "conversation_id": "1206304895957176320", "created_at": "2019-12-15 20:07:53 GMT", "date": "2019-12-15", "time": "20:07:53", "timezone": "+0000", "user_id": 3076794971, "username": "bishamparish", "name": "Villager", "place": "", "tweet": "Flood alert from #hurley to #bisham. Just issued!", "language": "en", "mentions": [], "urls": [], "photos": [], "replies_count": 0, "retweets_count": 0, "likes_count": 0, "hashtags": ["hurley", "bisham"], "cashtags": [], "link": "https://twitter.com/Bishamparish/status/1206304895957176320", "retweet": false, "quote_url": "", "video": 0, "thumbnail": "", "near": "", "geo": "54.153709,-4.529766,527km", "source": "", "user_rt_id": "", "user_rt": "", "retweet_id": "", "reply_to": [], "retweet_date": "", "translate": "", "trans_src": "", "trans_dest": ""}
{"id": 1206303202678841344, "conversation_id": "1206303202678841344", "created_at": "2019-12-15 20:01:10 GMT", "date": "2019-12-15", "time": "20:01:10", "timezone": "+0000", "user_id": 3446146816, "username": "riverlevelsuk", "name": "River Levels UK", "place": {"type": "Point", "coordinates": [51.742346, -1.263236]}, "tweet": "Flood Alert: River Thames and tributaries in the Oxford area 19:43 15 December  https://t.co/Fp14CuQvXd", "language": "en", "mentions": [], "urls": ["https://riverlevels.uk/flood-warning-river-thames-and-tributaries-in-the-oxford-area/1576440069"], "photos": [], "replies_count": 0, "retweets_count": 0, "likes_count": 0, "hashtags": [], "cashtags": [], "link": "https://twitter.com/RiverlevelsUK/status/1206303202678841344", "retweet": false, "quote_url": "", "video": 0, "thumbnail": "", "near": "", "geo": "54.153709,-4.529766,527km", "source": "", "user_rt_id": "", "user_rt": "", "retweet_id": "", "reply_to": [], "retweet_date": "", "translate": "", "trans_src": "", "trans_dest": ""}
{"id": 1206303179819945984, "conversation_id": "1206303179819945984", "created_at": "2019-12-15 20:01:04 GMT", "date": "2019-12-15", "time": "20:01:04", "timezone": "+0000", "user_id": 3446146816, "username": "riverlevelsuk", "name": "River Levels UK", "place": {"type": "Point", "coordinates": [51.653239, -1.237577]}, "tweet": "Flood Alert: River Thames for the Abingdon Area 19:44 15 December  https://t.co/MKLVCBLmZu", "language": "en", "mentions": [], "urls": ["https://riverlevels.uk/flood-warning-river-thames-for-the-abingdon-area/1576440064"], "photos": [], "replies_count": 0, "retweets_count": 0, "likes_count": 0, "hashtags": [], "cashtags": [], "link": "https://twitter.com/RiverlevelsUK/status/1206303179819945984", "retweet": false, "quote_url": "", "video": 0, "thumbnail": "", "near": "", "geo": "54.153709,-4.529766,527km", "source": "", "user_rt_id": "", "user_rt": "", "retweet_id": "", "reply_to": [], "retweet_date": "", "translate": "", "trans_src": "", "trans_dest": ""}
{"id": 1206303156751220742, "conversation_id": "1206303156751220742", "created_at": "2019-12-15 20:00:59 GMT", "date": "2019-12-15", "time": "20:00:59", "timezone": "+0000", "user_id": 3446146816, "username": "riverlevelsuk", "name": "River Levels UK", "place": {"type": "Point", "coordinates": [51.824961, -1.26464]}, "tweet": "Flood Alert: River Cherwell from Lower Heyford down to and including Oxford 19:44 15 December  https://t.co/B42cjD6he7", "language": "en", "mentions": [], "urls": ["https://riverlevels.uk/flood-warning-river-cherwell-from-lower-heyford-down-to-and-including-oxford/1576440058"], "photos": [], "replies_count": 0, "retweets_count": 0, "likes_count": 0, "hashtags": [], "cashtags": [], "link": "https://twitter.com/RiverlevelsUK/status/1206303156751220742", "retweet": false, "quote_url": "", "video": 0, "thumbnail": "", "near": "", "geo": "54.153709,-4.529766,527km", "source": "", "user_rt_id": "", "user_rt": "", "retweet_id": "", "reply_to": [], "retweet_date": "", "translate": "", "trans_src": "", "trans_dest": ""}
{"id": 1206303133900648449, "conversation_id": "1206303133900648449", "created_at": "2019-12-15 20:00:53 GMT", "date": "2019-12-15", "time": "20:00:53", "timezone": "+0000", "user_id": 3446146816, "username": "riverlevelsuk", "name": "River Levels UK", "place": {"type": "Point", "coordinates": [51.879668, -1.518783]}, "tweet": "Flood Alert: River Evenlode from Moreton in Marsh to Cassington 19:44 15 December  https://t.co/LqIGIHrUXq", "language": "en", "mentions": [], "urls": ["https://riverlevels.uk/flood-warning-river-evenlode-from-moreton-in-marsh-to-cassington-and-also-the-river-glyme-at-wootton-and-woodstock/1576440053"], "photos": [], "replies_count": 0, "retweets_count": 0, "likes_count": 0, "hashtags": [], "cashtags": [], "link": "https://twitter.com/RiverlevelsUK/status/1206303133900648449", "retweet": false, "quote_url": "", "video": 0, "thumbnail": "", "near": "", "geo": "54.153709,-4.529766,527km", "source": "", "user_rt_id": "", "user_rt": "", "retweet_id": "", "reply_to": [], "retweet_date": "", "translate": "", "trans_src": "", "trans_dest": ""}
{"id": 1206303108827099136, "conversation_id": "1206303108827099136", "created_at": "2019-12-15 20:00:47 GMT", "date": "2019-12-15", "time": "20:00:47", "timezone": "+0000", "user_id": 3446146816, "username": "riverlevelsuk", "name": "River Levels UK", "place": {"type": "Point", "coordinates": [51.46413, -1.143014]}, "tweet": "Flood Alert: River Pang from East Ilsley to Pangbourne and Sulham Brook 19:44 15 December  https://t.co/sdRPtAeoGJ", "language": "en", "mentions": [], "urls": ["https://riverlevels.uk/flood-warning-river-pang-from-east-ilsley-to-pangbourne-and-sulham-brook/1576440047"], "photos": [], "replies_count": 0, "retweets_count": 0, "likes_count": 0, "hashtags": [], "cashtags": [], "link": "https://twitter.com/RiverlevelsUK/status/1206303108827099136", "retweet": false, "quote_url": "", "video": 0, "thumbnail": "", "near": "", "geo": "54.153709,-4.529766,527km", "source": "", "user_rt_id": "", "user_rt": "", "retweet_id": "", "reply_to": [], "retweet_date": "", "translate": "", "trans_src": "", "trans_dest": ""}
{"id": 1206303086064623617, "conversation_id": "1206303086064623617", "created_at": "2019-12-15 20:00:42 GMT", "date": "2019-12-15", "time": "20:00:42", "timezone": "+0000", "user_id": 3446146816, "username": "riverlevelsuk", "name": "River Levels UK", "place": {"type": "Point", "coordinates": [51.415361, -1.101693]}, "tweet": "Flood Alert: River Kennet from Thatcham down to Reading 19:43 15 December  https://t.co/SbHrTZjs7d", "language": "en", "mentions": [], "urls": ["https://riverlevels.uk/flood-warning-river-kennet-from-thatcham-down-to-reading/1576440042"], "photos": [], "replies_count": 0, "retweets_count": 0, "likes_count": 0, "hashtags": [], "cashtags": [], "link": "https://twitter.com/RiverlevelsUK/status/1206303086064623617", "retweet": false, "quote_url": "", "video": 0, "thumbnail": "", "near": "", "geo": "54.153709,-4.529766,527km", "source": "", "user_rt_id": "", "user_rt": "", "retweet_id": "", "reply_to": [], "retweet_date": "", "translate": "", "trans_src": "", "trans_dest": ""}
{"id": 1206303061578268675, "conversation_id": "1206303061578268675", "created_at": "2019-12-15 20:00:36 GMT", "date": "2019-12-15", "time": "20:00:36", "timezone": "+0000", "user_id": 3446146816, "username": "riverlevelsuk", "name": "River Levels UK", "place": {"type": "Point", "coordinates": [52.060408, -1.299829]}, "tweet": "Flood Alert: River Cherwell from Charwelton to just above Upper Heyford 19:44 15 December  https://t.co/HnuRp05rCf", "language": "en", "mentions": [], "urls": ["https://riverlevels.uk/flood-warning-river-cherwell-from-charwelton-to-just-above-upper-heyford/1576440036"], "photos": [], "replies_count": 0, "retweets_count": 0, "likes_count": 0, "hashtags": [], "cashtags": [], "link": "https://twitter.com/RiverlevelsUK/status/1206303061578268675", "retweet": false, "quote_url": "", "video": 0, "thumbnail": "", "near": "", "geo": "54.153709,-4.529766,527km", "source": "", "user_rt_id": "", "user_rt": "", "retweet_id": "", "reply_to": [], "retweet_date": "", "translate": "", "trans_src": "", "trans_dest": ""}
{"id": 1206303038731882497, "conversation_id": "1206303038731882497", "created_at": "2019-12-15 20:00:31 GMT", "date": "2019-12-15", "time": "20:00:31", "timezone": "+0000", "user_id": 3446146816, "username": "riverlevelsuk", "name": "River Levels UK", "place": {"type": "Point", "coordinates": [51.617108, -1.873908]}, "tweet": "Flood Alert: Tributaries on the Upper River Thames above Cricklade 19:44 15 December  https://t.co/0TxEAWN1oS", "language": "en", "mentions": [], "urls": ["https://riverlevels.uk/flood-warning-the-tributaries-on-the-upper-river-thames-above-cricklade/1576440030"], "photos": [], "replies_count": 0, "retweets_count": 0, "likes_count": 0, "hashtags": [], "cashtags": [], "link": "https://twitter.com/RiverlevelsUK/status/1206303038731882497", "retweet": false, "quote_url": "", "video": 0, "thumbnail": "", "near": "", "geo": "54.153709,-4.529766,527km", "source": "", "user_rt_id": "", "user_rt": "", "retweet_id": "", "reply_to": [], "retweet_date": "", "translate": "", "trans_src": "", "trans_dest": ""}
{"id": 1206303015969398785, "conversation_id": "1206303015969398785", "created_at": "2019-12-15 20:00:25 GMT", "date": "2019-12-15", "time": "20:00:25", "timezone": "+0000", "user_id": 3446146816, "username": "riverlevelsuk", "name": "River Levels UK", "place": {"type": "Point", "coordinates": [51.718339, -1.771985]}, "tweet": "Flood Alert: River Coln and its tributaries 19:45 15 December  https://t.co/oZluGIig7F", "language": "en", "mentions": [], "urls": ["https://riverlevels.uk/flood-warning-river-coln-and-its-tributaries/1576440025"], "photos": [], "replies_count": 0, "retweets_count": 0, "likes_count": 0, "hashtags": [], "cashtags": [], "link": "https://twitter.com/RiverlevelsUK/status/1206303015969398785", "retweet": false, "quote_url": "", "video": 0, "thumbnail": "", "near": "", "geo": "54.153709,-4.529766,527km", "source": "", "user_rt_id": "", "user_rt": "", "retweet_id": "", "reply_to": [], "retweet_date": "", "translate": "", "trans_src": "", "trans_dest": ""}
{"id": 1206302993240481792, "conversation_id": "1206302993240481792", "created_at": "2019-12-15 20:00:20 GMT", "date": "2019-12-15", "time": "20:00:20", "timezone": "+0000", "user_id": 3446146816, "username": "riverlevelsuk", "name": "River Levels UK", "place": {"type": "Point", "coordinates": [52.273703, -0.395129]}, "tweet": "Flood Alert: River Kym in Cambridgeshire and Riseley Brook in Bedford Borough 19:35 15 December  https://t.co/lJheFITQpN", "language": "en", "mentions": [], "urls": ["https://riverlevels.uk/flood-warning-river-kym-and-tributaries/1576440019"], "photos": [], "replies_count": 0, "retweets_count": 0, "likes_count": 0, "hashtags": [], "cashtags": [], "link": "https://twitter.com/RiverlevelsUK/status/1206302993240481792", "retweet": false, "quote_url": "", "video": 0, "thumbnail": "", "near": "", "geo": "54.153709,-4.529766,527km", "source": "", "user_rt_id": "", "user_rt": "", "retweet_id": "", "reply_to": [], "retweet_date": "", "translate": "", "trans_src": "", "trans_dest": ""}
{"id": 1206300467132878849, "conversation_id": "1206300467132878849", "created_at": "2019-12-15 19:50:18 GMT", "date": "2019-12-15", "time": "19:50:18", "timezone": "+0000", "user_id": 3446146816, "username": "riverlevelsuk", "name": "River Levels UK", "place": {"type": "Point", "coordinates": [51.152027, -3.377201]}, "tweet": "Flood Alert: West Somerset Streams 19:26 15 December  https://t.co/IH6iCLzxg1", "language": "en", "mentions": [], "urls": ["https://riverlevels.uk/flood-warning-west-somerset-streams/1576439417"], "photos": [], "replies_count": 0, "retweets_count": 1, "likes_count": 0, "hashtags": [], "cashtags": [], "link": "https://twitter.com/RiverlevelsUK/status/1206300467132878849", "retweet": false, "quote_url": "", "video": 0, "thumbnail": "", "near": "", "geo": "54.153709,-4.529766,527km", "source": "", "user_rt_id": "", "user_rt": "", "retweet_id": "", "reply_to": [], "retweet_date": "", "translate": "", "trans_src": "", "trans_dest": ""}
